Workbook

Sheet Summary
A1: FLAVRLY
A2: Partner Settlement Report
A4: Report period | B4: 11 May 2026 — 17 May 2026
A5: Restaurant ID | B5: 18740308
A6: MID | B6: 145152
A7: Legal entity | B7: Sanaga Rajasekhara Reddy (sample)
A8: Restaurant name | B8: Combo Nation — Brodipet
A9: PAN | B9: ABUPR8322D
A10: GSTIN | B10: 37ABUPR8322D1Z8
A11: Settlement cycle | B11: Weekly (every Wednesday) — configurable to Daily
A12: Bank account | B12: XXXXXX7748 (masked)
A13: Generated by | B13: Flavrly Settlement Engine v1.0
A15: SETTLEMENT SUMMARY
A16: Delivered orders | B16: ='Payout Breakup'!C4 -> 7
A17: Cancelled / rejected orders | B17: ='Payout Breakup'!D4 -> 1
A18: Net order value (A) | B18: ='Payout Breakup'!E6 -> 4481
A19: Net deductions (C) | B19: ='Payout Breakup'!E20 -> 1064.3544
A20: Net additions (D) | B20: ='Payout Breakup'!E22 -> 40
A21: Net payout to bank | B21: ='Payout Breakup'!E25 -> 3226.6456
A22: Settled amount | B22: =SUMIF('Order Level'!AH7:AH100,"Settled",'Order Level'!AG7:AG100) -> 1940.5746
A23: Unsettled amount | B23: =SUMIF('Order Level'!AH7:AH100,"Pending",'Order Level'!AG7:AG100) -> 1286.071
A25: Note: amounts illustrative. GST/TCS/TDS rates are configurable; validate treatment with your finance team/CA. Flavrly is not a tax advisor.

Sheet Payout Breakup
A1: Payout Breakup
A2: P&L-style reconciliation from net order value to net bank payout
A3: S.no | B3: Particular | C3: Delivered Orders | D3: Cancelled / Rejected | E3: Total
B4: Number of orders | C4: =COUNTIFS('Order Level'!G7:G14,"Delivered") -> 7 | D4: =COUNTIFS('Order Level'!G7:G14,"<>Delivered") -> 1 | E4: =COUNTA('Order Level'!B7:B14) -> 8
A6: A | B6: Net order value (A) | C6: =SUMIFS('Order Level'!P7:P14,'Order Level'!$G$7:$G$14,"Delivered") -> 4206 | D6: =SUMIFS('Order Level'!P7:P14,'Order Level'!$G$7:$G$14,"<>Delivered") -> 275 | E6: =SUM('Order Level'!P7:P14) -> 4481
A7: 1 | B7: Subtotal (items total) | C7: =SUMIFS('Order Level'!I7:I14,'Order Level'!$G$7:$G$14,"Delivered") -> 4700 | D7: =SUMIFS('Order Level'!I7:I14,'Order Level'!$G$7:$G$14,"<>Delivered") -> 300 | E7: =SUM('Order Level'!I7:I14) -> 5000
A8: 2 | B8: Packaging charge | C8: =SUMIFS('Order Level'!J7:J14,'Order Level'!$G$7:$G$14,"Delivered") -> 125 | D8: =SUMIFS('Order Level'!J7:J14,'Order Level'!$G$7:$G$14,"<>Delivered") -> 10 | E8: =SUM('Order Level'!J7:J14) -> 135
A9: 3 | B9: Delivery charge from customer | C9: =SUMIFS('Order Level'!K7:K14,'Order Level'!$G$7:$G$14,"Delivered") -> 50 | D9: =SUMIFS('Order Level'!K7:K14,'Order Level'!$G$7:$G$14,"<>Delivered") -> 0 | E9: =SUM('Order Level'!K7:K14) -> 50
A10: 4 | B10: Restaurant discount (Promo) | C10: =SUMIFS('Order Level'!L7:L14,'Order Level'!$G$7:$G$14,"Delivered") -> 684 | D10: =SUMIFS('Order Level'!L7:L14,'Order Level'!$G$7:$G$14,"<>Delivered") -> 50 | E10: =SUM('Order Level'!L7:L14) -> 734
A11: 5 | B11: Restaurant discount (BOGO/Freebie) | C11: =SUMIFS('Order Level'!M7:M14,'Order Level'!$G$7:$G$14,"Delivered") -> 220 | D11: =SUMIFS('Order Level'!M7:M14,'Order Level'!$G$7:$G$14,"<>Delivered") -> 0 | E11: =SUM('Order Level'!M7:M14) -> 220
A12: 6 | B12: Delivery charge discount | C12: =SUMIFS('Order Level'!N7:N14,'Order Level'!$G$7:$G$14,"Delivered") -> 0 | D12: =SUMIFS('Order Level'!N7:N14,'Order Level'!$G$7:$G$14,"<>Delivered") -> 0 | E12: =SUM('Order Level'!N7:N14) -> 0
A13: 7 | B13: GST collected from customer | C13: =SUMIFS('Order Level'!O7:O14,'Order Level'!$G$7:$G$14,"Delivered") -> 235 | D13: =SUMIFS('Order Level'!O7:O14,'Order Level'!$G$7:$G$14,"<>Delivered") -> 15 | E13: =SUM('Order Level'!O7:O14) -> 250
A15: B | B15: Commission & fees | C15: =SUMIFS('Order Level'!U7:U14,'Order Level'!$G$7:$G$14,"Delivered") -> 769.08 | D15: =SUMIFS('Order Level'!U7:U14,'Order Level'!$G$7:$G$14,"<>Delivered") -> 51 | E15: =SUM('Order Level'!U7:U14) -> 820.08
A16: 8 | B16: Commission / service fee | C16: =SUMIFS('Order Level'!S7:S14,'Order Level'!$G$7:$G$14,"Delivered") -> 702.28 | D16: =SUMIFS('Order Level'!S7:S14,'Order Level'!$G$7:$G$14,"<>Delivered") -> 45 | E16: =SUM('Order Level'!S7:S14) -> 747.28
A17: 9 | B17: Payment mechanism fee | C17: =SUMIFS('Order Level'!T7:T14,'Order Level'!$G$7:$G$14,"Delivered") -> 66.8 | D17: =SUMIFS('Order Level'!T7:T14,'Order Level'!$G$7:$G$14,"<>Delivered") -> 6 | E17: =SUM('Order Level'!T7:T14) -> 72.8
A18: 10 | B18: GST on fees (18%) | C18: =SUMIFS('Order Level'!V7:V14,'Order Level'!$G$7:$G$14,"Delivered") -> 138.4344 | D18: =SUMIFS('Order Level'!V7:V14,'Order Level'!$G$7:$G$14,"<>Delivered") -> 9.18 | E18: =SUM('Order Level'!V7:V14) -> 147.6144
A19: 11 | B19: Govt charges — TCS (1%) + TDS 194O (1%) | C19: =SUMIFS('Order Level'!W7:W14,'Order Level'!$G$7:$G$14,"Delivered")+SUMIFS('Order Level'!X7:X14,'Order Level'!$G$7:$G$14,"Delivered") -> 90.81 | D19: =SUMIFS('Order Level'!W7:W14,'Order Level'!$G$7:$G$14,"<>Delivered")+SUMIFS('Order Level'!X7:X14,'Order Level'!$G$7:$G$14,"<>Delivered") -> 5.85 | E19: =SUM('Order Level'!W7:W14)+SUM('Order Level'!X7:X14) -> 96.66
A20: C | B20: Net deductions (C) = 8+9+10+11+other | C20: =SUMIFS('Order Level'!AE7:AE14,'Order Level'!$G$7:$G$14,"Delivered") -> 998.3244 | D20: =SUMIFS('Order Level'!AE7:AE14,'Order Level'!$G$7:$G$14,"<>Delivered") -> 66.03 | E20: =SUM('Order Level'!AE7:AE14) -> 1064.3544
A22: D | B22: Net additions (cancellation/promo recovery) | C22: =SUMIFS('Order Level'!AF7:AF14,'Order Level'!$G$7:$G$14,"Delivered") -> 0 | D22: =SUMIFS('Order Level'!AF7:AF14,'Order Level'!$G$7:$G$14,"<>Delivered") -> 40 | E22: =SUM('Order Level'!AF7:AF14) -> 40
A23: D2 | B23: Less: customer compensation + ads | C23: =SUMIFS('Order Level'!Z7:Z14,'Order Level'!$G$7:$G$14,"Delivered")+SUMIFS('Order Level'!AC7:AC14,'Order Level'!$G$7:$G$14,"Delivered") -> 150 | D23: =SUMIFS('Order Level'!Z7:Z14,'Order Level'!$G$7:$G$14,"<>Delivered")+SUMIFS('Order Level'!AC7:AC14,'Order Level'!$G$7:$G$14,"<>Delivered") -> 80 | E23: =SUM('Order Level'!Z7:Z14)+SUM('Order Level'!AC7:AC14) -> 230
A25: E | B25: NET PAYOUT (A − C + D) | C25: =SUMIFS('Order Level'!AG7:AG14,'Order Level'!$G$7:$G$14,"Delivered") -> 3057.6756 | D25: =SUMIFS('Order Level'!AG7:AG14,'Order Level'!$G$7:$G$14,"<>Delivered") -> 168.97 | E25: =SUM('Order Level'!AG7:AG14) -> 3226.6456

Sheet Order Level
A1: Order Level Breakup
A2: Per-order settlement detail — Customer Payable → Commissionable → Fees & Taxes → Deductions/Additions → Settlement
I5: CUSTOMER PAYABLE | Q5: COMMISSIONABLE / FEES & TAXES | Z5: DEDUCTIONS & ADDITIONS | AH5: SETTLEMENT
A6: S.no | B6: Order ID | C6: Order date | D6: Res. name | E6: Discount construct | F6: Mode of payment | G6: Order status | H6: Order type | I6: Subtotal | J6: Packaging | K6: Delivery charge (cust) | L6: Restaurant discount (Promo) | M6: Restaurant discount (BOGO/Freebie) | N6: Delivery charge discount | O6: GST collected from customer | P6: Net order value (A) | Q6: Commissionable value | R6: Commission % | S6: Commission / service fee | T6: Payment mechanism fee | U6: Service fee + payment fee | V6: GST on fees (18%) | W6: TCS (1%) | X6: TDS 194O (1%) | Y6: Govt charges (TCS+TDS+GST on fee) | Z6: Customer compensation | AA6: Cancellation recovery | AB6: Promo recovery adj | AC6: Ads deduction | AD6: Other order-level deduction | AE6: Net deductions (C) | AF6: Net additions (D) | AG6: Order level payout | AH6: Settlement status | AI6: Settlement date | AJ6: Bank UTR | AK6: Unsettled amount | AL6: Customer ID
A7: 1 | B7: ORD-SEED01 | C7: 2026-05-11 | D7: Combo Nation — Brodipet | E7: Flat ₹125 off | F7: UPI | G7: Delivered | H7: Delivery | I7: 480 | J7: 15 | K7: 0 | L7: 125 | M7: 0 | N7: 0 | O7: 24 | P7: =I7+J7+K7-L7-M7-N7+O7 -> 394 | Q7: =I7-L7-M7 -> 355 | R7: 0.18 | S7: =Q7*R7 -> 63.9 | T7: 9.6 | U7: =S7+T7 -> 73.5 | V7: =U7*0.18 -> 13.23 | W7: =P7*0.01 -> 3.94 | X7: =(I7+J7+K7)*0.01 -> 4.95 | Y7: =V7+W7+X7 -> 22.12 | Z7: 0 | AA7: 0 | AB7: 0 | AC7: 0 | AD7: 0 | AE7: =U7+V7+W7+X7+AD7 -> 95.62 | AF7: =AA7+AB7 -> 0 | AG7: =P7-AE7+AF7-Z7-AC7 -> 298.38 | AH7: Settled | AI7: 2026-05-21 | AJ7: CITIN26670847748 | AK7: =IF(AH7="Pending",AG7,0) -> 0 | AL7: C-1001
A8: 2 | B8: ORD-SEED02 | C8: 2026-05-11 | D8: Combo Nation — Brodipet | E8: BOGO | F8: COD | G8: Delivered | H8: Delivery | I8: 640 | J8: 20 | K8: 30 | L8: 0 | M8: 160 | N8: 0 | O8: 32 | P8: =I8+J8+K8-L8-M8-N8+O8 -> 562 | Q8: =I8-L8-M8 -> 480 | R8: 0.18 | S8: =Q8*R8 -> 86.4 | T8: 0 | U8: =S8+T8 -> 86.4 | V8: =U8*0.18 -> 15.552 | W8: =P8*0.01 -> 5.62 | X8: =(I8+J8+K8)*0.01 -> 6.9 | Y8: =V8+W8+X8 -> 28.072 | Z8: 0 | AA8: 0 | AB8: 0 | AC8: 0 | AD8: 0 | AE8: =U8+V8+W8+X8+AD8 -> 114.472 | AF8: =AA8+AB8 -> 0 | AG8: =P8-AE8+AF8-Z8-AC8 -> 447.528 | AH8: Settled | AI8: 2026-05-21 | AJ8: CITIN26670847748 | AK8: =IF(AH8="Pending",AG8,0) -> 0 | AL8: C-1002
A9: 3 | B9: ORD-SEED03 | C9: 2026-05-12 | D9: Combo Nation — Brodipet | E9: 50% off upto ₹300 | F9: RAZORPAY | G9: Delivered | H9: Delivery | I9: 900 | J9: 25 | K9: 0 | L9: 300 | M9: 0 | N9: 0 | O9: 45 | P9: =I9+J9+K9-L9-M9-N9+O9 -> 670 | Q9: =I9-L9-M9 -> 600 | R9: 0.2 | S9: =Q9*R9 -> 120 | T9: 18 | U9: =S9+T9 -> 138 | V9: =U9*0.18 -> 24.84 | W9: =P9*0.01 -> 6.7 | X9: =(I9+J9+K9)*0.01 -> 9.25 | Y9: =V9+W9+X9 -> 40.79 | Z9: 0 | AA9: 0 | AB9: 0 | AC9: 0 | AD9: 0 | AE9: =U9+V9+W9+X9+AD9 -> 178.79 | AF9: =AA9+AB9 -> 0 | AG9: =P9-AE9+AF9-Z9-AC9 -> 491.21 | AH9: Settled | AI9: 2026-05-21 | AJ9: CITIN26670847748 | AK9: =IF(AH9="Pending",AG9,0) -> 0 | AL9: C-1003
A10: 4 | B10: ORD-SEED04 | C10: 2026-05-13 | D10: Combo Nation — Brodipet | E10: None | F10: UPI | G10: Delivered | H10: Pickup | I10: 350 | J10: 0 | K10: 0 | L10: 0 | M10: 0 | N10: 0 | O10: 17.5 | P10: =I10+J10+K10-L10-M10-N10+O10 -> 367.5 | Q10: =I10-L10-M10 -> 350 | R10: 0.15 | S10: =Q10*R10 -> 52.5 | T10: 7 | U10: =S10+T10 -> 59.5 | V10: =U10*0.18 -> 10.71 | W10: =P10*0.01 -> 3.675 | X10: =(I10+J10+K10)*0.01 -> 3.5 | Y10: =V10+W10+X10 -> 17.885 | Z10: 0 | AA10: 0 | AB10: 0 | AC10: 0 | AD10: 0 | AE10: =U10+V10+W10+X10+AD10 -> 77.385 | AF10: =AA10+AB10 -> 0 | AG10: =P10-AE10+AF10-Z10-AC10 -> 290.115 | AH10: Settled | AI10: 2026-05-21 | AJ10: CITIN26670847748 | AK10: =IF(AH10="Pending",AG10,0) -> 0 | AL10: C-1004
A11: 5 | B11: ORD-SEED05 | C11: 2026-05-14 | D11: Combo Nation — Brodipet | E11: Happy Hour | F11: RAZORPAY | G11: Delivered | H11: Delivery | I11: 560 | J11: 15 | K11: 20 | L11: 84 | M11: 0 | N11: 0 | O11: 28 | P11: =I11+J11+K11-L11-M11-N11+O11 -> 539 | Q11: =I11-L11-M11 -> 476 | R11: 0.18 | S11: =Q11*R11 -> 85.68 | T11: 11.2 | U11: =S11+T11 -> 96.88 | V11: =U11*0.18 -> 17.4384 | W11: =P11*0.01 -> 5.39 | X11: =(I11+J11+K11)*0.01 -> 5.95 | Y11: =V11+W11+X11 -> 28.7784 | Z11: 0 | AA11: 0 | AB11: 0 | AC11: 0 | AD11: 0 | AE11: =U11+V11+W11+X11+AD11 -> 125.6584 | AF11: =AA11+AB11 -> 0 | AG11: =P11-AE11+AF11-Z11-AC11 -> 413.3416 | AH11: Settled | AI11: 2026-05-21 | AJ11: CITIN26670847748 | AK11: =IF(AH11="Pending",AG11,0) -> 0 | AL11: C-1005
A12: 6 | B12: ORD-SEED06 | C12: 2026-05-15 | D12: Combo Nation — Brodipet | E12: Freebie | F12: COD | G12: Delivered | H12: Delivery | I12: 720 | J12: 20 | K12: 0 | L12: 0 | M12: 60 | N12: 0 | O12: 36 | P12: =I12+J12+K12-L12-M12-N12+O12 -> 716 | Q12: =I12-L12-M12 -> 660 | R12: 0.18 | S12: =Q12*R12 -> 118.8 | T12: 0 | U12: =S12+T12 -> 118.8 | V12: =U12*0.18 -> 21.384 | W12: =P12*0.01 -> 7.16 | X12: =(I12+J12+K12)*0.01 -> 7.4 | Y12: =V12+W12+X12 -> 35.944 | Z12: 0 | AA12: 0 | AB12: 0 | AC12: 0 | AD12: 0 | AE12: =U12+V12+W12+X12+AD12 -> 154.744 | AF12: =AA12+AB12 -> 0 | AG12: =P12-AE12+AF12-Z12-AC12 -> 561.256 | AH12: Pending | AK12: =IF(AH12="Pending",AG12,0) -> 561.256 | AL12: C-1006
A13: 7 | B13: ORD-SEED07 | C13: 2026-05-16 | D13: Combo Nation — Brodipet | E13: Signup bonus | F13: UPI | G13: Cancelled | H13: Delivery | I13: 300 | J13: 10 | K13: 0 | L13: 50 | M13: 0 | N13: 0 | O13: 15 | P13: =I13+J13+K13-L13-M13-N13+O13 -> 275 | Q13: =I13-L13-M13 -> 250 | R13: 0.18 | S13: =Q13*R13 -> 45 | T13: 6 | U13: =S13+T13 -> 51 | V13: =U13*0.18 -> 9.18 | W13: =P13*0.01 -> 2.75 | X13: =(I13+J13+K13)*0.01 -> 3.1 | Y13: =V13+W13+X13 -> 15.03 | Z13: 80 | AA13: 40 | AB13: 0 | AC13: 0 | AD13: 0 | AE13: =U13+V13+W13+X13+AD13 -> 66.03 | AF13: =AA13+AB13 -> 40 | AG13: =P13-AE13+AF13-Z13-AC13 -> 168.97 | AH13: Pending | AK13: =IF(AH13="Pending",AG13,0) -> 168.97 | AL13: C-1007
A14: 8 | B14: ORD-SEED08 | C14: 2026-05-17 | D14: Combo Nation — Brodipet | E14: Flat ₹175 off | F14: RAZORPAY | G14: Delivered | H14: Delivery | I14: 1050 | J14: 30 | K14: 0 | L14: 175 | M14: 0 | N14: 0 | O14: 52.5 | P14: =I14+J14+K14-L14-M14-N14+O14 -> 957.5 | Q14: =I14-L14-M14 -> 875 | R14: 0.2 | S14: =Q14*R14 -> 175 | T14: 21 | U14: =S14+T14 -> 196 | V14: =U14*0.18 -> 35.28 | W14: =P14*0.01 -> 9.575 | X14: =(I14+J14+K14)*0.01 -> 10.8 | Y14: =V14+W14+X14 -> 55.655 | Z14: 0 | AA14: 0 | AB14: 0 | AC14: 150 | AD14: 0 | AE14: =U14+V14+W14+X14+AD14 -> 251.655 | AF14: =AA14+AB14 -> 0 | AG14: =P14-AE14+AF14-Z14-AC14 -> 555.845 | AH14: Pending | AK14: =IF(AH14="Pending",AG14,0) -> 555.845 | AL14: C-1008

Sheet Additions & Deductions
A1: Additions & Deductions Details
A2: Ads, adjustments, recoveries and credit/debit notes with settlement status
A4: Type | B4: Description | C4: Invoice / Order ID | D4: Date | E4: Settlement status | F4: Total amount | G4: Adjusted amount | H4: Outstanding
A5: ADS | B5: Visibility ads (banner) | C5: 37052390 | D5: 2026-05-20 | E5: Settled | F5: 2941.21 | G5: 2941.21 | H5: 0
A6: Adjustment | B6: Promo recovery — ORD-SEED07 | C6: ORD-SEED07 | D6: 2026-05-16 | E6: Pending | F6: 40 | G6: 0 | H6: 40
A7: Credit note | B7: Customer compensation — ORD-SEED07 | C7: ORD-SEED07 | D7: 2026-05-16 | E7: Pending | F7: 80 | G7: 0 | H7: 80
A8: Recovery | B8: Cancellation recovery — ORD-SEED07 | C8: ORD-SEED07 | D8: 2026-05-16 | E8: Pending | F8: 40 | G8: 40 | H8: 0
A9: Other | B9: Express order fee waiver | C9: - | D9: 2026-05-17 | E9: Settled | F9: 0 | G9: 0 | H9: 0

Sheet Discounts Summary
A1: Offers & Discounts Summary
A2: Per discount construct: orders, subtotal, discount given, effective %
A4: Discount Construct | B4: Orders | C4: Subtotal (₹) | D4: Discount given (₹) | E4: Discount/order (₹) | F4: Effective Discount %
A5: Flat ₹125 off | B5: =COUNTIF('Order Level'!E7:E14,"Flat ₹125 off") -> 1 | C5: =SUMIF('Order Level'!E7:E14,"Flat ₹125 off",'Order Level'!I7:I14) -> 480 | D5: =SUMIF('Order Level'!E7:E14,"Flat ₹125 off",'Order Level'!L7:L14)+SUMIF('Order Level'!E7:E14,"Flat ₹125 off",'Order Level'!M7:M14) -> 125 | E5: =IF(B5=0,0,D5/B5) -> 125 | F5: =IF(C5=0,0,D5/C5) -> 0.26041667
A6: BOGO | B6: =COUNTIF('Order Level'!E7:E14,"BOGO") -> 1 | C6: =SUMIF('Order Level'!E7:E14,"BOGO",'Order Level'!I7:I14) -> 640 | D6: =SUMIF('Order Level'!E7:E14,"BOGO",'Order Level'!L7:L14)+SUMIF('Order Level'!E7:E14,"BOGO",'Order Level'!M7:M14) -> 160 | E6: =IF(B6=0,0,D6/B6) -> 160 | F6: =IF(C6=0,0,D6/C6) -> 0.25
A7: 50% off upto ₹300 | B7: =COUNTIF('Order Level'!E7:E14,"50% off upto ₹300") -> 1 | C7: =SUMIF('Order Level'!E7:E14,"50% off upto ₹300",'Order Level'!I7:I14) -> 900 | D7: =SUMIF('Order Level'!E7:E14,"50% off upto ₹300",'Order Level'!L7:L14)+SUMIF('Order Level'!E7:E14,"50% off upto ₹300",'Order Level'!M7:M14) -> 300 | E7: =IF(B7=0,0,D7/B7) -> 300 | F7: =IF(C7=0,0,D7/C7) -> 0.33333333
A8: Happy Hour | B8: =COUNTIF('Order Level'!E7:E14,"Happy Hour") -> 1 | C8: =SUMIF('Order Level'!E7:E14,"Happy Hour",'Order Level'!I7:I14) -> 560 | D8: =SUMIF('Order Level'!E7:E14,"Happy Hour",'Order Level'!L7:L14)+SUMIF('Order Level'!E7:E14,"Happy Hour",'Order Level'!M7:M14) -> 84 | E8: =IF(B8=0,0,D8/B8) -> 84 | F8: =IF(C8=0,0,D8/C8) -> 0.15
A9: Freebie | B9: =COUNTIF('Order Level'!E7:E14,"Freebie") -> 1 | C9: =SUMIF('Order Level'!E7:E14,"Freebie",'Order Level'!I7:I14) -> 720 | D9: =SUMIF('Order Level'!E7:E14,"Freebie",'Order Level'!L7:L14)+SUMIF('Order Level'!E7:E14,"Freebie",'Order Level'!M7:M14) -> 60 | E9: =IF(B9=0,0,D9/B9) -> 60 | F9: =IF(C9=0,0,D9/C9) -> 0.083333333
A10: Signup bonus | B10: =COUNTIF('Order Level'!E7:E14,"Signup bonus") -> 1 | C10: =SUMIF('Order Level'!E7:E14,"Signup bonus",'Order Level'!I7:I14) -> 300 | D10: =SUMIF('Order Level'!E7:E14,"Signup bonus",'Order Level'!L7:L14)+SUMIF('Order Level'!E7:E14,"Signup bonus",'Order Level'!M7:M14) -> 50 | E10: =IF(B10=0,0,D10/B10) -> 50 | F10: =IF(C10=0,0,D10/C10) -> 0.16666667
A11: Flat ₹175 off | B11: =COUNTIF('Order Level'!E7:E14,"Flat ₹175 off") -> 1 | C11: =SUMIF('Order Level'!E7:E14,"Flat ₹175 off",'Order Level'!I7:I14) -> 1050 | D11: =SUMIF('Order Level'!E7:E14,"Flat ₹175 off",'Order Level'!L7:L14)+SUMIF('Order Level'!E7:E14,"Flat ₹175 off",'Order Level'!M7:M14) -> 175 | E11: =IF(B11=0,0,D11/B11) -> 175 | F11: =IF(C11=0,0,D11/C11) -> 0.16666667
A12: None | B12: =COUNTIF('Order Level'!E7:E14,"None") -> 1 | C12: =SUMIF('Order Level'!E7:E14,"None",'Order Level'!I7:I14) -> 350 | D12: =SUMIF('Order Level'!E7:E14,"None",'Order Level'!L7:L14)+SUMIF('Order Level'!E7:E14,"None",'Order Level'!M7:M14) -> 0 | E12: =IF(B12=0,0,D12/B12) -> 0 | F12: =IF(C12=0,0,D12/C12) -> 0
A13: TOTAL | B13: =SUM(B5:B12) -> 8 | C13: =SUM(C5:C12) -> 5000 | D13: =SUM(D5:D12) -> 954 | F13: =IF(C13=0,0,D13/C13) -> 0.1908

Sheet Tax & Compliance
A1: Tax & Compliance (India)
A2: GST / TCS (Sec 52) / TDS (Sec 194O) breakdown — rates configurable; confirm with your CA
A4: Component | B4: Basis | C4: Rate (configurable) | D4: Period total (₹)
A5: GST collected from customer (on food) | B5: Order subtotal | C5: 5% (illustrative) | D5: =SUM('Order Level'!O7:O14) -> 250
A6: Commission / service fee | B6: Commissionable value | C6: Per restaurant (15–20%) | D6: =SUM('Order Level'!S7:S14) -> 747.28
A7: Payment mechanism fee | B7: Net order value | C7: ~2% (online) | D7: =SUM('Order Level'!T7:T14) -> 72.8
A8: GST on platform fees | B8: Service + payment fee | C8: 18% | D8: =SUM('Order Level'!V7:V14) -> 147.6144
A9: TCS under GST (Sec 52) | B9: Net order value | C9: 1% | D9: =SUM('Order Level'!W7:W14) -> 44.81
A10: TDS under Income Tax (Sec 194O) | B10: Gross order value | C10: 1% | D10: =SUM('Order Level'!X7:X14) -> 51.85
A11: Total government charges | B11: TCS + TDS + GST on fees | C11: - | D11: =SUM('Order Level'!Y7:Y14) -> 244.2744
A14: Flavrly (as the e-commerce operator) collects & deposits TCS/TDS and issues GST-compliant invoices + TCS/TDS certificates. Rates above are illustrative defaults and must be validated by your finance team/CA. Flavrly is not a tax advisor.

Sheet Glossary
A1: Glossary
A2: Definition of every term used in this settlement report
A4: S.no | B4: Term | C4: Definition
A5: 1 | B5: Subtotal (items total) | C5: Gross total of dishes/items ordered, before charges, taxes and discounts.
A6: 2 | B6: Packaging charge | C6: Cost set by the restaurant for packaging, passed to the customer.
A7: 3 | B7: Delivery charge from customer | C7: Delivery fee charged to the customer (restaurant share, if any).
A8: 4 | B8: Restaurant discount (Promo) | C8: Coupon/percentage/flat promo discount funded by the restaurant.
A9: 5 | B9: Restaurant discount (BOGO/Freebie) | C9: Value of BOGO, freebie, happy-hour or item-level offers funded by the restaurant.
A10: 6 | B10: Delivery charge discount | C10: Delivery fee waived/subsidised by the restaurant.
A11: 7 | B11: GST collected from customer | C11: GST charged to the customer on food (deposited per tax rules).
A12: A | B12: Net order value | C12: Subtotal + Packaging + Delivery − Discounts + GST collected. Base figure for settlement.
A13: - | B13: Commissionable value | C13: Value on which platform commission is charged (subtotal − restaurant discounts).
A14: 8 | B14: Commission / service fee | C14: Platform commission = commissionable value × commission %.
A15: 9 | B15: Payment mechanism fee | C15: Online payment gateway fee on the order.
... A24: - | B24: Discount construct | C24: The named offer applied (BOGO, coupon, happy hour, freebie, signup bonus).

Sheet Flavrly Add-ons
A1: Flavrly Differentiators — 'Even Better' Add-ons
A2: What Flavrly does beyond a static weekly settlement xlsx
A4: # | B4: Differentiator | C4: What it does | D4: Client benefit
A5: 1 | B5: Live settlement dashboard | C5: Real-time payable balance + projected next payout, not just a weekly file | D5: Always-on visibility into cash
A6: 2 | B6: Configurable / Daily settlement | C6: Daily, T+1 or weekly cycles per restaurant (Zomato = fixed weekly) | D6: Faster, smoother cash flow
A7: 3 | B7: Instant payout (early settlement) | C7: Optional advance against confirmed receivables | D7: Liquidity on demand
A8: 4 | B8: Auto-reconciliation & dispute flags | C8: Auto-detects mismatches (refund vs charge, COD shortfall, commission anomaly) + one-click raise | D8: Catches money leakage automatically
A9: 5 | B9: Commission transparency | C9: Per-item/category commission + effective take-rate trend | D9: Negotiate & optimise with data
A10: 6 | B10: Tax-ready exports | C10: Auto GST invoice + TCS/TDS certificates + GSTR-friendly CSV | D10: Painless tax filing
A11: 7 | B11: Multi-format & auto-delivery | C11: xlsx + PDF + JSON/API + email + WhatsApp summary, auto-sent each cycle | D11: Report comes to you, any format
A12: 8 | B12: Interactive drill-down | C12: Filter by branch, payment mode, discount construct; group/brand rollup for multi-outlet owners | D12: Answers questions instantly
A13: 9 | B13: Discount ROI insights | C13: Effective discount % vs incremental orders; suggests under/over-performing offers | D13: Spend promo budget smarter
A14: 10 | B14: Payout forecasting | C14: Projects next payout from in-flight orders | D14: Plan working capital
A15: 11 | B15: Immutable audit trail | C15: Every line traces to order + audit log; tamper-evident | D15: Trust & dispute-proof
... A19: 15 | B19: Wallet-first refund clarity | C19: Flavrly's wallet-first refunds shown distinctly from gateway reversals | D19: Cleaner refund accounting
